mcp_tour/__init__.py
mcp_tour/server.py
mcp_tour/hosts/__init__.py
mcp_tour/hosts/claude_desktop.py
mcp_tour/hosts/cursor.py
mcp_tour-0.1.11.dist-info/METADATA
mcp_tour-0.1.11.dist-info/WHEEL
mcp_tour-0.1.11.dist-info/entry_points.txt
mcp_tour-0.1.11.dist-info/licenses/LICENSE
mcp_tour-0.1.11.dist-info/RECORD
