Metadata-Version: 2.4
Name: mcp-tour
Version: 0.1.11
Summary: MCP server providing Korea Tourism Organization APIs
Project-URL: Repository, https://github.com/tjwodud04/mcp-tour.git
Author-email: tjwodud04 <tjwodud04@gmail.com>
License-File: LICENSE
Requires-Python: >=3.10
Requires-Dist: certifi>=2024.2.2
Requires-Dist: fastmcp>=0.4.1
Requires-Dist: httpx>=0.28.1
Requires-Dist: pydantic>=2.10.6
Requires-Dist: python-dotenv>=1.0.0
